{
  "nodes": {
    "41566.282": {
      "votes": {},
      "initial_weight": 0.5,
      "final_weight": 0.5
    },
    "41566.570": {
      "votes": {},
      "initial_weight": 0.5,
      "final_weight": 0.5
    },
    "41566.435": {
      "votes": {},
      "initial_weight": 0.5,
      "final_weight": 0.5
    },
    "41566.13": {
      "votes": {},
      "initial_weight": 0.5,
      "final_weight": 0.9520170883149072
    },
    "41566.568": {
      "votes": {},
      "initial_weight": 0.5,
      "final_weight": 0.5
    },
    "41566.211": {
      "votes": {
        "3": 1
      },
      "initial_weight": 0.75,
      "final_weight": 0.75
    },
    "41566.264": {
      "votes": {
        "3": 1
      },
      "initial_weight": 0.75,
      "final_weight": 0.512855579868709
    },
    "41566.406": {
      "votes": {
        "3": 1
      },
      "initial_weight": 0.75,
      "final_weight": 0.75
    },
    "41566.388": {
      "votes": {},
      "initial_weight": 0.5,
      "final_weight": 0.5
    },
    "41566.315": {
      "votes": {},
      "initial_weight": 0.5,
      "final_weight": 0.5
    },
    "41566.7": {
      "votes": {
        "3": 2,
        "2": 1
      },
      "initial_weight": 0.6666666666666666,
      "final_weight": 0.9761361895484548
    },
    "41566.38": {
      "votes": {},
      "initial_weight": 0.5,
      "final_weight": 0.5
    },
    "41566.134": {
      "votes": {},
      "initial_weight": 0.5,
      "final_weight": 0.5
    },
    "41566.202": {
      "votes": {},
      "initial_weight": 0.5,
      "final_weight": 0.46526763405285976
    },
    "41566.248": {
      "votes": {},
      "initial_weight": 0.5,
      "final_weight": 0.47058823529411764
    },
    "41566.125": {
      "votes": {},
      "initial_weight": 0.5,
      "final_weight": 0.5
    },
    "41566.472": {
      "votes": {},
      "initial_weight": 0.5,
      "final_weight": 0.5
    },
    "41566.17": {
      "votes": {},
      "initial_weight": 0.5,
      "final_weight": 0.5977673752276164
    },
    "41566.356": {
      "votes": {},
      "initial_weight": 0.5,
      "final_weight": 0.5
    },
    "41566.36": {
      "votes": {
        "4": 1
      },
      "initial_weight": 1.0,
      "final_weight": 1.0
    },
    "41566.416": {
      "votes": {
        "3": 1
      },
      "initial_weight": 0.75,
      "final_weight": 0.75
    },
    "41566.160": {
      "votes": {},
      "initial_weight": 0.5,
      "final_weight": 0.5
    },
    "41566.375": {
      "votes": {},
      "initial_weight": 0.5,
      "final_weight": 0.5
    },
    "41566.274": {
      "votes": {},
      "initial_weight": 0.5,
      "final_weight": 0.5
    },
    "41566.488": {
      "votes": {},
      "initial_weight": 0.5,
      "final_weight": 0.5
    },
    "41566.208": {
      "votes": {},
      "initial_weight": 0.5,
      "final_weight": 0.6
    },
    "41566.380": {
      "votes": {},
      "initial_weight": 0.5,
      "final_weight": 0.5
    },
    "41566.227": {
      "votes": {},
      "initial_weight": 0.5,
      "final_weight": 0.9400983649018
    },
    "41566.544": {
      "votes": {},
      "initial_weight": 0.5,
      "final_weight": 0.5
    },
    "41566.239": {
      "votes": {
        "3": 1
      },
      "initial_weight": 0.75,
      "final_weight": 0.75
    },
    "41566.297": {
      "votes": {},
      "initial_weight": 0.5,
      "final_weight": 0.8461538461538461
    },
    "41566.149": {
      "votes": {},
      "initial_weight": 0.5,
      "final_weight": 0.5
    },
    "41566.186": {
      "votes": {
        "1": 1,
        "2": 1,
        "3": 1
      },
      "initial_weight": 0.5,
      "final_weight": 0.6319909638499737
    },
    "41566.302": {
      "votes": {},
      "initial_weight": 0.5,
      "final_weight": 0.75
    },
    "41566.162": {
      "votes": {},
      "initial_weight": 0.5,
      "final_weight": 0.5
    },
    "41566.538": {
      "votes": {},
      "initial_weight": 0.5,
      "final_weight": 0.5
    },
    "41566.213": {
      "votes": {
        "3": 1
      },
      "initial_weight": 0.75,
      "final_weight": 0.75
    },
    "41566.233": {
      "votes": {},
      "initial_weight": 0.5,
      "final_weight": 0.6411589973257175
    },
    "41566.311": {
      "votes": {},
      "initial_weight": 0.5,
      "final_weight": 0.5
    },
    "41566.317": {
      "votes": {},
      "initial_weight": 0.5,
      "final_weight": 0.37719595917408444
    },
    "41566.443": {
      "votes": {},
      "initial_weight": 0.5,
      "final_weight": 0.6
    },
    "41566.5": {
      "votes": {},
      "initial_weight": 0.5,
      "final_weight": 0.42788531305515454
    },
    "41566.40": {
      "votes": {
        "4": 1
      },
      "initial_weight": 1.0,
      "final_weight": 1.0
    },
    "41566.517": {
      "votes": {},
      "initial_weight": 0.5,
      "final_weight": 0.6
    },
    "41566.392": {
      "votes": {},
      "initial_weight": 0.5,
      "final_weight": 0.5
    },
    "41566.418": {
      "votes": {
        "3": 1
      },
      "initial_weight": 0.75,
      "final_weight": 0.75
    },
    "41566.180": {
      "votes": {
        "0": 1,
        "3": 1
      },
      "initial_weight": 0.375,
      "final_weight": 0.6875
    },
    "41566.276": {
      "votes": {
        "4": 1
      },
      "initial_weight": 1.0,
      "final_weight": 1.0
    },
    "41566.231": {
      "votes": {
        "3": 1
      },
      "initial_weight": 0.75,
      "final_weight": 0.75
    },
    "41566.430": {
      "votes": {},
      "initial_weight": 0.5,
      "final_weight": 0.6
    },
    "41566.288": {
      "votes": {},
      "initial_weight": 0.5,
      "final_weight": 0.6176034324474018
    },
    "41566.250": {
      "votes": {
        "3": 1
      },
      "initial_weight": 0.75,
      "final_weight": 0.75
    },
    "41566.272": {
      "votes": {
        "3": 1
      },
      "initial_weight": 0.75,
      "final_weight": 0.77322206095791
    },
    "41566.345": {
      "votes": {},
      "initial_weight": 0.5,
      "final_weight": 0.5
    },
    "41566.437": {
      "votes": {},
      "initial_weight": 0.5,
      "final_weight": 0.5
    },
    "41566.122": {
      "votes": {},
      "initial_weight": 0.5,
      "final_weight": 0.5
    },
    "41566.519": {
      "votes": {},
      "initial_weight": 0.5,
      "final_weight": 0.5
    },
    "41566.339": {
      "votes": {},
      "initial_weight": 0.5,
      "final_weight": 0.5
    },
    "41566.326": {
      "votes": {},
      "initial_weight": 0.5,
      "final_weight": 0.6
    },
    "41566.426": {
      "votes": {},
      "initial_weight": 0.5,
      "final_weight": 0.5
    },
    "41566.515": {
      "votes": {},
      "initial_weight": 0.5,
      "final_weight": 0.5
    },
    "41566.132": {
      "votes": {
        "3": 1
      },
      "initial_weight": 0.75,
      "final_weight": 0.75
    },
    "41566.32": {
      "votes": {},
      "initial_weight": 0.5,
      "final_weight": 0.5
    },
    "41566.536": {
      "votes": {},
      "initial_weight": 0.5,
      "final_weight": 0.5
    },
    "41566.555": {
      "votes": {},
      "initial_weight": 0.5,
      "final_weight": 0.5
    },
    "41566.561": {
      "votes": {},
      "initial_weight": 0.5,
      "final_weight": 0.5
    },
    "41566.278": {
      "votes": {},
      "initial_weight": 0.5,
      "final_weight": 0.5
    },
    "41566.358": {
      "votes": {},
      "initial_weight": 0.5,
      "final_weight": 0.6
    },
    "41566.504": {
      "votes": {},
      "initial_weight": 0.5,
      "final_weight": 0.5
    },
    "41566.3": {
      "votes": {
        "1": 1,
        "3": 1,
        "2": 1
      },
      "initial_weight": 0.5,
      "final_weight": 0.8889990268237604
    },
    "41566.183": {
      "votes": {},
      "initial_weight": 0.5,
      "final_weight": 0.5
    },
    "41566.28": {
      "votes": {},
      "initial_weight": 0.5,
      "final_weight": 0.441827189055758
    },
    "41566.564": {
      "votes": {},
      "initial_weight": 0.5,
      "final_weight": 0.5
    },
    "41566.494": {
      "votes": {},
      "initial_weight": 0.5,
      "final_weight": 0.5
    },
    "41566.262": {
      "votes": {},
      "initial_weight": 0.5,
      "final_weight": 0.6
    },
    "41566.270": {
      "votes": {
        "3": 1
      },
      "initial_weight": 0.75,
      "final_weight": 0.75
    },
    "41566.401": {
      "votes": {},
      "initial_weight": 0.5,
      "final_weight": 0.7201491042406157
    },
    "41566.124": {
      "votes": {},
      "initial_weight": 0.5,
      "final_weight": 0.5
    },
    "41566.491": {
      "votes": {},
      "initial_weight": 0.5,
      "final_weight": 0.7737556561085973
    },
    "41566.164": {
      "votes": {
        "3": 1
      },
      "initial_weight": 0.75,
      "final_weight": 0.75
    },
    "41566.225": {
      "votes": {},
      "initial_weight": 0.5,
      "final_weight": 0.5
    },
    "41566.252": {
      "votes": {},
      "initial_weight": 0.5,
      "final_weight": 0.5
    },
    "41566.482": {
      "votes": {},
      "initial_weight": 0.5,
      "final_weight": 0.5
    },
    "41566.464": {
      "votes": {},
      "initial_weight": 0.5,
      "final_weight": 0.7737556561085973
    },
    "41566.448": {
      "votes": {},
      "initial_weight": 0.5,
      "final_weight": 0.5
    },
    "41566.323": {
      "votes": {},
      "initial_weight": 0.5,
      "final_weight": 0.5
    },
    "41566.299": {
      "votes": {},
      "initial_weight": 0.5,
      "final_weight": 0.5
    },
    "41566.368": {
      "votes": {},
      "initial_weight": 0.5,
      "final_weight": 0.5
    },
    "41566.450": {
      "votes": {},
      "initial_weight": 0.5,
      "final_weight": 0.5
    },
    "41566.245": {
      "votes": {},
      "initial_weight": 0.5,
      "final_weight": 0.5
    },
    "41566.200": {
      "votes": {
        "3": 1
      },
      "initial_weight": 0.75,
      "final_weight": 0.75
    },
    "41566.295": {
      "votes": {},
      "initial_weight": 0.5,
      "final_weight": 0.5
    },
    "41566.445": {
      "votes": {},
      "initial_weight": 0.5,
      "final_weight": 0.5
    },
    "41566.441": {
      "votes": {},
      "initial_weight": 0.5,
      "final_weight": 0.5
    },
    "41566.331": {
      "votes": {},
      "initial_weight": 0.5,
      "final_weight": 0.5
    },
    "41566.525": {
      "votes": {},
      "initial_weight": 0.5,
      "final_weight": 0.6
    },
    "41566.506": {
      "votes": {},
      "initial_weight": 0.5,
      "final_weight": 0.5
    },
    "41566.474": {
      "votes": {},
      "initial_weight": 0.5,
      "final_weight": 0.5
    },
    "41566.256": {
      "votes": {
        "3": 1
      },
      "initial_weight": 0.75,
      "final_weight": 0.75
    },
    "41566.566": {
      "votes": {},
      "initial_weight": 0.5,
      "final_weight": 0.5
    },
    "41566.333": {
      "votes": {},
      "initial_weight": 0.5,
      "final_weight": 0.5
    },
    "41566.219": {
      "votes": {},
      "initial_weight": 0.5,
      "final_weight": 0.5
    },
    "41566.557": {
      "votes": {},
      "initial_weight": 0.5,
      "final_weight": 0.5
    },
    "41566.254": {
      "votes": {},
      "initial_weight": 0.5,
      "final_weight": 0.6799999999999999
    },
    "41566.34": {
      "votes": {
        "4": 1
      },
      "initial_weight": 1.0,
      "final_weight": 1.0
    },
    "41566.428": {
      "votes": {},
      "initial_weight": 0.5,
      "final_weight": 0.5
    },
    "41566.480": {
      "votes": {},
      "initial_weight": 0.5,
      "final_weight": 0.75
    },
    "41566.382": {
      "votes": {},
      "initial_weight": 0.5,
      "final_weight": 0.5
    },
    "41566.243": {
      "votes": {
        "4": 1
      },
      "initial_weight": 1.0,
      "final_weight": 1.0
    },
    "41566.178": {
      "votes": {},
      "initial_weight": 0.5,
      "final_weight": 0.5
    },
    "41566.321": {
      "votes": {},
      "initial_weight": 0.5,
      "final_weight": 0.5
    },
    "41566.510": {
      "votes": {},
      "initial_weight": 0.5,
      "final_weight": 0.5
    },
    "41566.458": {
      "votes": {},
      "initial_weight": 0.5,
      "final_weight": 0.36764705882352944
    },
    "41566.194": {
      "votes": {},
      "initial_weight": 0.5,
      "final_weight": 0.5
    },
    "41566.502": {
      "votes": {},
      "initial_weight": 0.5,
      "final_weight": 0.47058823529411764
    },
    "41566.386": {
      "votes": {},
      "initial_weight": 0.5,
      "final_weight": 0.5
    },
    "41566.42": {
      "votes": {},
      "initial_weight": 0.5,
      "final_weight": 0.5
    },
    "41566.266": {
      "votes": {
        "2": 1
      },
      "initial_weight": 0.5,
      "final_weight": 0.6799999999999999
    },
    "41566.420": {
      "votes": {},
      "initial_weight": 0.5,
      "final_weight": 0.5
    },
    "41566.223": {
      "votes": {
        "3": 1
      },
      "initial_weight": 0.75,
      "final_weight": 0.8
    },
    "41566.309": {
      "votes": {
        "3": 1
      },
      "initial_weight": 0.75,
      "final_weight": 0.75
    },
    "41566.19": {
      "votes": {},
      "initial_weight": 0.5,
      "final_weight": 0.5830129549270898
    },
    "41566.456": {
      "votes": {},
      "initial_weight": 0.5,
      "final_weight": 0.5595351495522957
    },
    "41566.128": {
      "votes": {},
      "initial_weight": 0.5,
      "final_weight": 0.5
    },
    "41566.44": {
      "votes": {
        "3": 1
      },
      "initial_weight": 0.75,
      "final_weight": 0.75
    },
    "41566.460": {
      "votes": {},
      "initial_weight": 0.5,
      "final_weight": 0.5
    },
    "41566.188": {
      "votes": {
        "3": 1
      },
      "initial_weight": 0.75,
      "final_weight": 0.8
    },
    "41566.21": {
      "votes": {
        "3": 1
      },
      "initial_weight": 0.75,
      "final_weight": 0.84
    },
    "41566.280": {
      "votes": {
        "3": 1
      },
      "initial_weight": 0.75,
      "final_weight": 0.75
    },
    "41566.147": {
      "votes": {},
      "initial_weight": 0.5,
      "final_weight": 0.6
    },
    "41566.396": {
      "votes": {},
      "initial_weight": 0.5,
      "final_weight": 0.5
    },
    "41566.410": {
      "votes": {},
      "initial_weight": 0.5,
      "final_weight": 0.5
    },
    "41566.408": {
      "votes": {},
      "initial_weight": 0.5,
      "final_weight": 0.5
    },
    "41566.130": {
      "votes": {},
      "initial_weight": 0.5,
      "final_weight": 0.8869417750141323
    },
    "41566.338": {
      "votes": {},
      "initial_weight": 0.5,
      "final_weight": 0.75
    },
    "41566.166": {
      "votes": {},
      "initial_weight": 0.5,
      "final_weight": 0.5
    },
    "41566.512": {
      "votes": {},
      "initial_weight": 0.5,
      "final_weight": 0.5
    },
    "41566.325": {
      "votes": {},
      "initial_weight": 0.5,
      "final_weight": 0.5
    },
    "41566.260": {
      "votes": {
        "2": 1
      },
      "initial_weight": 0.5,
      "final_weight": 0.5
    },
    "41566.462": {
      "votes": {},
      "initial_weight": 0.5,
      "final_weight": 0.4
    },
    "41566.414": {
      "votes": {},
      "initial_weight": 0.5,
      "final_weight": 0.5
    },
    "41566.500": {
      "votes": {},
      "initial_weight": 0.5,
      "final_weight": 0.6
    },
    "41566.452": {
      "votes": {
        "0": 1,
        "4": 2,
        "3": 1
      },
      "initial_weight": 0.6875,
      "final_weight": 0.763894484368446
    },
    "41566.172": {
      "votes": {},
      "initial_weight": 0.5,
      "final_weight": 0.5
    },
    "41566.533": {
      "votes": {},
      "initial_weight": 0.5,
      "final_weight": 0.5
    },
    "41566.384": {
      "votes": {},
      "initial_weight": 0.5,
      "final_weight": 0.5
    },
    "41566.229": {
      "votes": {
        "3": 1
      },
      "initial_weight": 0.75,
      "final_weight": 0.75
    },
    "41566.198": {
      "votes": {},
      "initial_weight": 0.5,
      "final_weight": 0.32
    },
    "41566.258": {
      "votes": {},
      "initial_weight": 0.5,
      "final_weight": 0.5545657015590201
    },
    "41566.217": {
      "votes": {},
      "initial_weight": 0.5,
      "final_weight": 0.9038923594425756
    },
    "41566.15": {
      "votes": {},
      "initial_weight": 0.5,
      "final_weight": 0.6282959693344174
    },
    "41566.478": {
      "votes": {},
      "initial_weight": 0.5,
      "final_weight": 0.5
    },
    "41566.196": {
      "votes": {},
      "initial_weight": 0.5,
      "final_weight": 0.6
    },
    "41566.484": {
      "votes": {},
      "initial_weight": 0.5,
      "final_weight": 0.5
    },
    "41566.439": {
      "votes": {},
      "initial_weight": 0.5,
      "final_weight": 0.6
    },
    "41566.498": {
      "votes": {},
      "initial_weight": 0.5,
      "final_weight": 0.4
    },
    "41566.486": {
      "votes": {},
      "initial_weight": 0.5,
      "final_weight": 0.5
    },
    "41566.11": {
      "votes": {},
      "initial_weight": 0.5,
      "final_weight": 0.5773763977065683
    },
    "41566.508": {
      "votes": {},
      "initial_weight": 0.5,
      "final_weight": 0.5
    },
    "41566.527": {
      "votes": {},
      "initial_weight": 0.5,
      "final_weight": 0.5
    },
    "41566.9": {
      "votes": {},
      "initial_weight": 0.5,
      "final_weight": 0.5
    },
    "41566.221": {
      "votes": {
        "3": 1
      },
      "initial_weight": 0.75,
      "final_weight": 0.75
    },
    "41566.30": {
      "votes": {
        "3": 1
      },
      "initial_weight": 0.75,
      "final_weight": 0.1499999999999999
    },
    "41566.158": {
      "votes": {},
      "initial_weight": 0.5,
      "final_weight": 0.4
    },
    "41566.190": {
      "votes": {
        "3": 1
      },
      "initial_weight": 0.75,
      "final_weight": 0.8105382416368624
    },
    "41566.432": {
      "votes": {
        "3": 2,
        "0": 1
      },
      "initial_weight": 0.5,
      "final_weight": 0.5
    },
    "41566.313": {
      "votes": {},
      "initial_weight": 0.5,
      "final_weight": 0.5
    },
    "41566.168": {
      "votes": {
        "3": 1
      },
      "initial_weight": 0.75,
      "final_weight": 0.75
    },
    "41566.156": {
      "votes": {},
      "initial_weight": 0.5,
      "final_weight": 0.5
    },
    "41566.531": {
      "votes": {},
      "initial_weight": 0.5,
      "final_weight": 0.5
    },
    "41566.206": {
      "votes": {},
      "initial_weight": 0.5,
      "final_weight": 0.9105330930992879
    },
    "41566.170": {
      "votes": {},
      "initial_weight": 0.5,
      "final_weight": 0.5
    },
    "41566.523": {
      "votes": {},
      "initial_weight": 0.5,
      "final_weight": 0.5
    },
    "41566.241": {
      "votes": {},
      "initial_weight": 0.5,
      "final_weight": 0.9
    },
    "41566.215": {
      "votes": {
        "3": 1
      },
      "initial_weight": 0.75,
      "final_weight": 0.75
    },
    "41566.521": {
      "votes": {},
      "initial_weight": 0.5,
      "final_weight": 0.75
    },
    "41566.328": {
      "votes": {},
      "initial_weight": 0.5,
      "final_weight": 0.7424259426924555
    },
    "41566.23": {
      "votes": {},
      "initial_weight": 0.5,
      "final_weight": 0.6
    },
    "41566.399": {
      "votes": {},
      "initial_weight": 0.5,
      "final_weight": 0.5
    },
    "41566.284": {
      "votes": {},
      "initial_weight": 0.5,
      "final_weight": 0.7086206896551724
    },
    "41566.268": {
      "votes": {
        "4": 1
      },
      "initial_weight": 1.0,
      "final_weight": 1.0
    },
    "41566.319": {
      "votes": {},
      "initial_weight": 0.5,
      "final_weight": 0.5
    },
    "41566.364": {
      "votes": {},
      "initial_weight": 0.5,
      "final_weight": 0.5
    },
    "41566.546": {
      "votes": {},
      "initial_weight": 0.5,
      "final_weight": 0.5
    },
    "41566.404": {
      "votes": {},
      "initial_weight": 0.5,
      "final_weight": 0.5
    },
    "41566.412": {
      "votes": {},
      "initial_weight": 0.5,
      "final_weight": 0.5
    }
  },
  "edges": {
    "41566.7": {
      "successor_id": "41566.3",
      "relation": 1.0
    },
    "41566.19": {
      "successor_id": "41566.17",
      "relation": 1.0
    },
    "41566.186": {
      "successor_id": "41566.3",
      "relation": 1.0
    },
    "41566.206": {
      "successor_id": "41566.5",
      "relation": -1.0
    },
    "41566.432": {
      "successor_id": "41566.3",
      "relation": -1.0
    },
    "41566.452": {
      "successor_id": "41566.3",
      "relation": 1.0
    },
    "41566.23": {
      "successor_id": "41566.7",
      "relation": 1.0
    },
    "41566.172": {
      "successor_id": "41566.7",
      "relation": 1.0
    },
    "41566.11": {
      "successor_id": "41566.7",
      "relation": 1.0
    },
    "41566.188": {
      "successor_id": "41566.7",
      "relation": 1.0
    },
    "41566.299": {
      "successor_id": "41566.13",
      "relation": 1.0
    },
    "41566.309": {
      "successor_id": "41566.7",
      "relation": 1.0
    },
    "41566.321": {
      "successor_id": "41566.338",
      "relation": 1.0
    },
    "41566.241": {
      "successor_id": "41566.7",
      "relation": -1.0
    },
    "41566.544": {
      "successor_id": "41566.7",
      "relation": 1.0
    },
    "41566.491": {
      "successor_id": "41566.7",
      "relation": 1.0
    },
    "41566.122": {
      "successor_id": "41566.19",
      "relation": 1.0
    },
    "41566.125": {
      "successor_id": "41566.19",
      "relation": 1.0
    },
    "41566.134": {
      "successor_id": "41566.19",
      "relation": -1.0
    },
    "41566.168": {
      "successor_id": "41566.19",
      "relation": -1.0
    },
    "41566.328": {
      "successor_id": "41566.19",
      "relation": 1.0
    },
    "41566.418": {
      "successor_id": "41566.19",
      "relation": -1.0
    },
    "41566.254": {
      "successor_id": "41566.19",
      "relation": 1.0
    },
    "41566.416": {
      "successor_id": "41566.19",
      "relation": -1.0
    },
    "41566.464": {
      "successor_id": "41566.19",
      "relation": 1.0
    },
    "41566.396": {
      "successor_id": "41566.186",
      "relation": 1.0
    },
    "41566.439": {
      "successor_id": "41566.186",
      "relation": -1.0
    },
    "41566.15": {
      "successor_id": "41566.186",
      "relation": 1.0
    },
    "41566.248": {
      "successor_id": "41566.186",
      "relation": 1.0
    },
    "41566.498": {
      "successor_id": "41566.186",
      "relation": -1.0
    },
    "41566.211": {
      "successor_id": "41566.206",
      "relation": 1.0
    },
    "41566.245": {
      "successor_id": "41566.5",
      "relation": 1.0
    },
    "41566.227": {
      "successor_id": "41566.206",
      "relation": 1.0
    },
    "41566.13": {
      "successor_id": "41566.206",
      "relation": 1.0
    },
    "41566.564": {
      "successor_id": "41566.206",
      "relation": -1.0
    },
    "41566.474": {
      "successor_id": "41566.432",
      "relation": -1.0
    },
    "41566.546": {
      "successor_id": "41566.432",
      "relation": 1.0
    },
    "41566.28": {
      "successor_id": "41566.452",
      "relation": 1.0
    },
    "41566.233": {
      "successor_id": "41566.452",
      "relation": -1.0
    },
    "41566.456": {
      "successor_id": "41566.452",
      "relation": 1.0
    },
    "41566.284": {
      "successor_id": "41566.452",
      "relation": 1.0
    },
    "41566.566": {
      "successor_id": "41566.452",
      "relation": -1.0
    },
    "41566.42": {
      "successor_id": "41566.23",
      "relation": 1.0
    },
    "41566.156": {
      "successor_id": "41566.23",
      "relation": 1.0
    },
    "41566.426": {
      "successor_id": "41566.23",
      "relation": -1.0
    },
    "41566.428": {
      "successor_id": "41566.23",
      "relation": -1.0
    },
    "41566.311": {
      "successor_id": "41566.23",
      "relation": 1.0
    },
    "41566.9": {
      "successor_id": "41566.11",
      "relation": 1.0
    },
    "41566.5": {
      "successor_id": "41566.11",
      "relation": 1.0
    },
    "41566.162": {
      "successor_id": "41566.11",
      "relation": -1.0
    },
    "41566.213": {
      "successor_id": "41566.188",
      "relation": -1.0
    },
    "41566.215": {
      "successor_id": "41566.188",
      "relation": 1.0
    },
    "41566.494": {
      "successor_id": "41566.188",
      "relation": 1.0
    },
    "41566.243": {
      "successor_id": "41566.241",
      "relation": 1.0
    },
    "41566.252": {
      "successor_id": "41566.241",
      "relation": 1.0
    },
    "41566.268": {
      "successor_id": "41566.241",
      "relation": 1.0
    },
    "41566.278": {
      "successor_id": "41566.241",
      "relation": -1.0
    },
    "41566.525": {
      "successor_id": "41566.491",
      "relation": 1.0
    },
    "41566.531": {
      "successor_id": "41566.491",
      "relation": 1.0
    },
    "41566.124": {
      "successor_id": "41566.125",
      "relation": 1.0
    },
    "41566.128": {
      "successor_id": "41566.125",
      "relation": 1.0
    },
    "41566.166": {
      "successor_id": "41566.125",
      "relation": -1.0
    },
    "41566.460": {
      "successor_id": "41566.125",
      "relation": -1.0
    },
    "41566.386": {
      "successor_id": "41566.134",
      "relation": 1.0
    },
    "41566.388": {
      "successor_id": "41566.134",
      "relation": -1.0
    },
    "41566.326": {
      "successor_id": "41566.328",
      "relation": 1.0
    },
    "41566.333": {
      "successor_id": "41566.328",
      "relation": 1.0
    },
    "41566.339": {
      "successor_id": "41566.328",
      "relation": -1.0
    },
    "41566.338": {
      "successor_id": "41566.328",
      "relation": -1.0
    },
    "41566.345": {
      "successor_id": "41566.328",
      "relation": 1.0
    },
    "41566.358": {
      "successor_id": "41566.328",
      "relation": -1.0
    },
    "41566.368": {
      "successor_id": "41566.328",
      "relation": 1.0
    },
    "41566.401": {
      "successor_id": "41566.328",
      "relation": 1.0
    },
    "41566.256": {
      "successor_id": "41566.254",
      "relation": 1.0
    },
    "41566.412": {
      "successor_id": "41566.464",
      "relation": 1.0
    },
    "41566.410": {
      "successor_id": "41566.464",
      "relation": 1.0
    },
    "41566.32": {
      "successor_id": "41566.464",
      "relation": 1.0
    },
    "41566.408": {
      "successor_id": "41566.464",
      "relation": 1.0
    },
    "41566.462": {
      "successor_id": "41566.464",
      "relation": -1.0
    },
    "41566.414": {
      "successor_id": "41566.464",
      "relation": -1.0
    },
    "41566.536": {
      "successor_id": "41566.396",
      "relation": 1.0
    },
    "41566.538": {
      "successor_id": "41566.396",
      "relation": -1.0
    },
    "41566.441": {
      "successor_id": "41566.439",
      "relation": 1.0
    },
    "41566.180": {
      "successor_id": "41566.15",
      "relation": 1.0
    },
    "41566.323": {
      "successor_id": "41566.15",
      "relation": 1.0
    },
    "41566.325": {
      "successor_id": "41566.15",
      "relation": 1.0
    },
    "41566.430": {
      "successor_id": "41566.15",
      "relation": -1.0
    },
    "41566.448": {
      "successor_id": "41566.15",
      "relation": -1.0
    },
    "41566.280": {
      "successor_id": "41566.248",
      "relation": -1.0
    },
    "41566.282": {
      "successor_id": "41566.248",
      "relation": 1.0
    },
    "41566.392": {
      "successor_id": "41566.498",
      "relation": -1.0
    },
    "41566.229": {
      "successor_id": "41566.227",
      "relation": 1.0
    },
    "41566.231": {
      "successor_id": "41566.227",
      "relation": 1.0
    },
    "41566.250": {
      "successor_id": "41566.227",
      "relation": 1.0
    },
    "41566.190": {
      "successor_id": "41566.227",
      "relation": 1.0
    },
    "41566.406": {
      "successor_id": "41566.227",
      "relation": 1.0
    },
    "41566.443": {
      "successor_id": "41566.227",
      "relation": -1.0
    },
    "41566.450": {
      "successor_id": "41566.227",
      "relation": -1.0
    },
    "41566.158": {
      "successor_id": "41566.13",
      "relation": -1.0
    },
    "41566.288": {
      "successor_id": "41566.13",
      "relation": 1.0
    },
    "41566.302": {
      "successor_id": "41566.13",
      "relation": 1.0
    },
    "41566.217": {
      "successor_id": "41566.13",
      "relation": 1.0
    },
    "41566.17": {
      "successor_id": "41566.13",
      "relation": 1.0
    },
    "41566.478": {
      "successor_id": "41566.13",
      "relation": -1.0
    },
    "41566.208": {
      "successor_id": "41566.13",
      "relation": 1.0
    },
    "41566.30": {
      "successor_id": "41566.28",
      "relation": 1.0
    },
    "41566.264": {
      "successor_id": "41566.28",
      "relation": -1.0
    },
    "41566.239": {
      "successor_id": "41566.233",
      "relation": 1.0
    },
    "41566.317": {
      "successor_id": "41566.233",
      "relation": 1.0
    },
    "41566.523": {
      "successor_id": "41566.233",
      "relation": -1.0
    },
    "41566.458": {
      "successor_id": "41566.456",
      "relation": 1.0
    },
    "41566.38": {
      "successor_id": "41566.284",
      "relation": 1.0
    },
    "41566.437": {
      "successor_id": "41566.284",
      "relation": -1.0
    },
    "41566.297": {
      "successor_id": "41566.284",
      "relation": 1.0
    },
    "41566.568": {
      "successor_id": "41566.566",
      "relation": 1.0
    },
    "41566.570": {
      "successor_id": "41566.566",
      "relation": -1.0
    },
    "41566.527": {
      "successor_id": "41566.525",
      "relation": 1.0
    },
    "41566.331": {
      "successor_id": "41566.326",
      "relation": 1.0
    },
    "41566.364": {
      "successor_id": "41566.333",
      "relation": -1.0
    },
    "41566.382": {
      "successor_id": "41566.333",
      "relation": 1.0
    },
    "41566.384": {
      "successor_id": "41566.338",
      "relation": 1.0
    },
    "41566.356": {
      "successor_id": "41566.358",
      "relation": 1.0
    },
    "41566.130": {
      "successor_id": "41566.401",
      "relation": 1.0
    },
    "41566.170": {
      "successor_id": "41566.32",
      "relation": -1.0
    },
    "41566.380": {
      "successor_id": "41566.32",
      "relation": 1.0
    },
    "41566.472": {
      "successor_id": "41566.462",
      "relation": -1.0
    },
    "41566.178": {
      "successor_id": "41566.180",
      "relation": 1.0
    },
    "41566.183": {
      "successor_id": "41566.180",
      "relation": 1.0
    },
    "41566.435": {
      "successor_id": "41566.430",
      "relation": 1.0
    },
    "41566.194": {
      "successor_id": "41566.190",
      "relation": 1.0
    },
    "41566.196": {
      "successor_id": "41566.190",
      "relation": 1.0
    },
    "41566.202": {
      "successor_id": "41566.190",
      "relation": 1.0
    },
    "41566.276": {
      "successor_id": "41566.190",
      "relation": -1.0
    },
    "41566.445": {
      "successor_id": "41566.443",
      "relation": 1.0
    },
    "41566.160": {
      "successor_id": "41566.158",
      "relation": -1.0
    },
    "41566.258": {
      "successor_id": "41566.288",
      "relation": 1.0
    },
    "41566.399": {
      "successor_id": "41566.302",
      "relation": 1.0
    },
    "41566.420": {
      "successor_id": "41566.302",
      "relation": 1.0
    },
    "41566.219": {
      "successor_id": "41566.217",
      "relation": 1.0
    },
    "41566.221": {
      "successor_id": "41566.217",
      "relation": 1.0
    },
    "41566.223": {
      "successor_id": "41566.217",
      "relation": 1.0
    },
    "41566.21": {
      "successor_id": "41566.17",
      "relation": -1.0
    },
    "41566.44": {
      "successor_id": "41566.17",
      "relation": 1.0
    },
    "41566.561": {
      "successor_id": "41566.208",
      "relation": 1.0
    },
    "41566.34": {
      "successor_id": "41566.30",
      "relation": -1.0
    },
    "41566.36": {
      "successor_id": "41566.30",
      "relation": -1.0
    },
    "41566.266": {
      "successor_id": "41566.264",
      "relation": -1.0
    },
    "41566.319": {
      "successor_id": "41566.317",
      "relation": 1.0
    },
    "41566.500": {
      "successor_id": "41566.317",
      "relation": -1.0
    },
    "41566.502": {
      "successor_id": "41566.317",
      "relation": -1.0
    },
    "41566.517": {
      "successor_id": "41566.458",
      "relation": -1.0
    },
    "41566.375": {
      "successor_id": "41566.38",
      "relation": 1.0
    },
    "41566.40": {
      "successor_id": "41566.38",
      "relation": -1.0
    },
    "41566.486": {
      "successor_id": "41566.38",
      "relation": 1.0
    },
    "41566.313": {
      "successor_id": "41566.297",
      "relation": 1.0
    },
    "41566.315": {
      "successor_id": "41566.297",
      "relation": 1.0
    },
    "41566.515": {
      "successor_id": "41566.297",
      "relation": 1.0
    },
    "41566.132": {
      "successor_id": "41566.130",
      "relation": 1.0
    },
    "41566.147": {
      "successor_id": "41566.130",
      "relation": 1.0
    },
    "41566.404": {
      "successor_id": "41566.130",
      "relation": 1.0
    },
    "41566.295": {
      "successor_id": "41566.196",
      "relation": 1.0
    },
    "41566.272": {
      "successor_id": "41566.202",
      "relation": -1.0
    },
    "41566.274": {
      "successor_id": "41566.202",
      "relation": 1.0
    },
    "41566.260": {
      "successor_id": "41566.258",
      "relation": 1.0
    },
    "41566.262": {
      "successor_id": "41566.258",
      "relation": 1.0
    },
    "41566.480": {
      "successor_id": "41566.258",
      "relation": -1.0
    },
    "41566.225": {
      "successor_id": "41566.223",
      "relation": 1.0
    },
    "41566.164": {
      "successor_id": "41566.21",
      "relation": 1.0
    },
    "41566.270": {
      "successor_id": "41566.266",
      "relation": 1.0
    },
    "41566.504": {
      "successor_id": "41566.500",
      "relation": 1.0
    },
    "41566.521": {
      "successor_id": "41566.502",
      "relation": -1.0
    },
    "41566.533": {
      "successor_id": "41566.502",
      "relation": 1.0
    },
    "41566.519": {
      "successor_id": "41566.517",
      "relation": 1.0
    },
    "41566.510": {
      "successor_id": "41566.40",
      "relation": 1.0
    },
    "41566.512": {
      "successor_id": "41566.40",
      "relation": -1.0
    },
    "41566.506": {
      "successor_id": "41566.486",
      "relation": -1.0
    },
    "41566.508": {
      "successor_id": "41566.486",
      "relation": 1.0
    },
    "41566.149": {
      "successor_id": "41566.147",
      "relation": 1.0
    },
    "41566.198": {
      "successor_id": "41566.272",
      "relation": 1.0
    },
    "41566.488": {
      "successor_id": "41566.262",
      "relation": 1.0
    },
    "41566.482": {
      "successor_id": "41566.480",
      "relation": 1.0
    },
    "41566.484": {
      "successor_id": "41566.480",
      "relation": 1.0
    },
    "41566.555": {
      "successor_id": "41566.521",
      "relation": 1.0
    },
    "41566.557": {
      "successor_id": "41566.521",
      "relation": 1.0
    },
    "41566.200": {
      "successor_id": "41566.198",
      "relation": -1.0
    }
  }
}