{
  "nodes": {
    "38268.0": {
      "votes": {},
      "initial_weight": 0.5,
      "final_weight": 0.5
    },
    "38268.3": {
      "votes": {
        "4": 6,
        "0": 3
      },
      "initial_weight": 0.6666666666666666,
      "final_weight": 0.8846336135470165
    },
    "38268.7": {
      "votes": {
        "3": 2,
        "0": 1,
        "4": 1
      },
      "initial_weight": 0.625,
      "final_weight": 0.593881695002706
    },
    "38268.13": {
      "votes": {
        "3": 1,
        "0": 1,
        "4": 3
      },
      "initial_weight": 0.75,
      "final_weight": 0.7887933785064278
    },
    "38268.25": {
      "votes": {
        "0": 1,
        "2": 1,
        "1": 2,
        "3": 1,
        "4": 3
      },
      "initial_weight": 0.59375,
      "final_weight": 0.8442557097379877
    },
    "38268.84": {
      "votes": {
        "4": 1,
        "3": 1,
        "0": 1
      },
      "initial_weight": 0.5833333333333334,
      "final_weight": 0.8361152336255072
    },
    "38268.219": {
      "votes": {
        "0": 1
      },
      "initial_weight": 0.0,
      "final_weight": 0.0
    },
    "38268.89": {
      "votes": {},
      "initial_weight": 0.5,
      "final_weight": 0.511002444987775
    },
    "38268.5": {
      "votes": {},
      "initial_weight": 0.5,
      "final_weight": 0.49504950495049505
    },
    "38268.23": {
      "votes": {},
      "initial_weight": 0.5,
      "final_weight": 0.49964006311815096
    },
    "38268.575": {
      "votes": {},
      "initial_weight": 0.5,
      "final_weight": 0.3941121551150581
    },
    "38268.151": {
      "votes": {},
      "initial_weight": 0.5,
      "final_weight": 0.3184814004142234
    },
    "38268.95": {
      "votes": {
        "4": 1
      },
      "initial_weight": 1.0,
      "final_weight": 1.0
    },
    "38268.87": {
      "votes": {},
      "initial_weight": 0.5,
      "final_weight": 0.4807692307692308
    },
    "38268.417": {
      "votes": {},
      "initial_weight": 0.5,
      "final_weight": 0.6951219512195121
    },
    "38268.421": {
      "votes": {},
      "initial_weight": 0.5,
      "final_weight": 0.7737556561085973
    },
    "38268.461": {
      "votes": {},
      "initial_weight": 0.5,
      "final_weight": 0.44046485044770434
    },
    "38268.105": {
      "votes": {
        "0": 1,
        "4": 1
      },
      "initial_weight": 0.5,
      "final_weight": 0.5
    },
    "38268.261": {
      "votes": {
        "2": 1,
        "4": 1
      },
      "initial_weight": 0.75,
      "final_weight": 0.7682437991220178
    },
    "38268.563": {
      "votes": {
        "4": 1
      },
      "initial_weight": 1.0,
      "final_weight": 1.0
    },
    "38268.78": {
      "votes": {},
      "initial_weight": 0.5,
      "final_weight": 0.6
    },
    "38268.239": {
      "votes": {},
      "initial_weight": 0.5,
      "final_weight": 0.6094594594594595
    },
    "38268.431": {
      "votes": {},
      "initial_weight": 0.5,
      "final_weight": 0.4
    },
    "38268.433": {
      "votes": {
        "1": 1
      },
      "initial_weight": 0.25,
      "final_weight": 0.36751065429932317
    },
    "38268.137": {
      "votes": {},
      "initial_weight": 0.5,
      "final_weight": 0.5
    },
    "38268.153": {
      "votes": {},
      "initial_weight": 0.5,
      "final_weight": 0.19026527051369424
    },
    "38268.27": {
      "votes": {},
      "initial_weight": 0.5,
      "final_weight": 0.2075074724368019
    },
    "38268.227": {
      "votes": {},
      "initial_weight": 0.5,
      "final_weight": 0.5
    },
    "38268.573": {
      "votes": {},
      "initial_weight": 0.5,
      "final_weight": 0.5
    },
    "38268.93": {
      "votes": {},
      "initial_weight": 0.5,
      "final_weight": 0.4
    },
    "38268.115": {
      "votes": {},
      "initial_weight": 0.5,
      "final_weight": 0.75
    },
    "38268.141": {
      "votes": {},
      "initial_weight": 0.5,
      "final_weight": 0.5
    },
    "38268.313": {
      "votes": {},
      "initial_weight": 0.5,
      "final_weight": 0.6
    },
    "38268.41": {
      "votes": {},
      "initial_weight": 0.5,
      "final_weight": 0.5
    },
    "38268.19": {
      "votes": {},
      "initial_weight": 0.5,
      "final_weight": 0.6000000000000001
    },
    "38268.402": {
      "votes": {},
      "initial_weight": 0.5,
      "final_weight": 0.5
    },
    "38268.584": {
      "votes": {},
      "initial_weight": 0.5,
      "final_weight": 0.5
    },
    "38268.65": {
      "votes": {},
      "initial_weight": 0.5,
      "final_weight": 0.4
    },
    "38268.75": {
      "votes": {},
      "initial_weight": 0.5,
      "final_weight": 0.3571759616870076
    },
    "38268.282": {
      "votes": {},
      "initial_weight": 0.5,
      "final_weight": 0.2840160875297493
    },
    "38268.588": {
      "votes": {},
      "initial_weight": 0.5,
      "final_weight": 0.5
    },
    "38268.594": {
      "votes": {},
      "initial_weight": 0.5,
      "final_weight": 0.5183381088825215
    },
    "38268.139": {
      "votes": {},
      "initial_weight": 0.5,
      "final_weight": 0.75
    },
    "38268.182": {
      "votes": {},
      "initial_weight": 0.5,
      "final_weight": 0.4310344827586207
    },
    "38268.295": {
      "votes": {},
      "initial_weight": 0.5,
      "final_weight": 0.4
    },
    "38268.339": {
      "votes": {},
      "initial_weight": 0.5,
      "final_weight": 0.6
    },
    "38268.378": {
      "votes": {},
      "initial_weight": 0.5,
      "final_weight": 0.49504950495049505
    },
    "38268.384": {
      "votes": {
        "2": 1
      },
      "initial_weight": 0.5,
      "final_weight": 0.4999999047421767
    },
    "38268.97": {
      "votes": {},
      "initial_weight": 0.5,
      "final_weight": 0.7237569060773481
    },
    "38268.99": {
      "votes": {
        "0": 1
      },
      "initial_weight": 0.0,
      "final_weight": 0.0
    },
    "38268.101": {
      "votes": {},
      "initial_weight": 0.5,
      "final_weight": 0.4
    },
    "38268.117": {
      "votes": {},
      "initial_weight": 0.5,
      "final_weight": 0.5
    },
    "38268.176": {
      "votes": {},
      "initial_weight": 0.5,
      "final_weight": 0.6
    },
    "38268.231": {
      "votes": {},
      "initial_weight": 0.5,
      "final_weight": 0.4
    },
    "38268.376": {
      "votes": {},
      "initial_weight": 0.5,
      "final_weight": 0.5
    },
    "38268.419": {
      "votes": {},
      "initial_weight": 0.5,
      "final_weight": 0.6
    },
    "38268.467": {
      "votes": {},
      "initial_weight": 0.5,
      "final_weight": 0.4
    },
    "38268.499": {
      "votes": {},
      "initial_weight": 0.5,
      "final_weight": 0.6
    },
    "38268.423": {
      "votes": {},
      "initial_weight": 0.5,
      "final_weight": 0.5
    },
    "38268.425": {
      "votes": {},
      "initial_weight": 0.5,
      "final_weight": 0.5
    },
    "38268.427": {
      "votes": {},
      "initial_weight": 0.5,
      "final_weight": 0.5
    },
    "38268.447": {
      "votes": {},
      "initial_weight": 0.5,
      "final_weight": 0.4
    },
    "38268.549": {
      "votes": {},
      "initial_weight": 0.5,
      "final_weight": 0.36764705882352944
    },
    "38268.123": {
      "votes": {},
      "initial_weight": 0.5,
      "final_weight": 0.5
    },
    "38268.286": {
      "votes": {},
      "initial_weight": 0.5,
      "final_weight": 0.5
    },
    "38268.82": {
      "votes": {},
      "initial_weight": 0.5,
      "final_weight": 0.32
    },
    "38268.125": {
      "votes": {
        "1": 1
      },
      "initial_weight": 0.25,
      "final_weight": 0.125
    },
    "38268.31": {
      "votes": {},
      "initial_weight": 0.5,
      "final_weight": 0.3355704697986577
    },
    "38268.266": {
      "votes": {},
      "initial_weight": 0.5,
      "final_weight": 0.5
    },
    "38268.172": {
      "votes": {},
      "initial_weight": 0.5,
      "final_weight": 0.5
    },
    "38268.528": {
      "votes": {},
      "initial_weight": 0.5,
      "final_weight": 0.5
    },
    "38268.526": {
      "votes": {},
      "initial_weight": 0.5,
      "final_weight": 0.5
    },
    "38268.561": {
      "votes": {},
      "initial_weight": 0.5,
      "final_weight": 0.5
    },
    "38268.451": {
      "votes": {},
      "initial_weight": 0.5,
      "final_weight": 0.5
    },
    "38268.494": {
      "votes": {},
      "initial_weight": 0.5,
      "final_weight": 0.5
    },
    "38268.496": {
      "votes": {},
      "initial_weight": 0.5,
      "final_weight": 0.5
    },
    "38268.241": {
      "votes": {},
      "initial_weight": 0.5,
      "final_weight": 0.5
    },
    "38268.243": {
      "votes": {},
      "initial_weight": 0.5,
      "final_weight": 0.5
    },
    "38268.245": {
      "votes": {},
      "initial_weight": 0.5,
      "final_weight": 0.47058823529411764
    },
    "38268.455": {
      "votes": {},
      "initial_weight": 0.5,
      "final_weight": 0.5
    },
    "38268.168": {
      "votes": {},
      "initial_weight": 0.5,
      "final_weight": 0.5
    },
    "38268.435": {
      "votes": {},
      "initial_weight": 0.5,
      "final_weight": 0.5
    },
    "38268.437": {
      "votes": {},
      "initial_weight": 0.5,
      "final_weight": 0.5
    },
    "38268.157": {
      "votes": {},
      "initial_weight": 0.5,
      "final_weight": 0.2241042507234649
    },
    "38268.162": {
      "votes": {
        "4": 1
      },
      "initial_weight": 1.0,
      "final_weight": 1.0
    },
    "38268.359": {
      "votes": {},
      "initial_weight": 0.5,
      "final_weight": 0.5
    },
    "38268.43": {
      "votes": {},
      "initial_weight": 0.5,
      "final_weight": 0.5
    },
    "38268.51": {
      "votes": {},
      "initial_weight": 0.5,
      "final_weight": 0.3127545400988704
    },
    "38268.45": {
      "votes": {},
      "initial_weight": 0.5,
      "final_weight": 0.5
    },
    "38268.127": {
      "votes": {},
      "initial_weight": 0.5,
      "final_weight": 0.25
    },
    "38268.166": {
      "votes": {},
      "initial_weight": 0.5,
      "final_weight": 0.75
    },
    "38268.229": {
      "votes": {},
      "initial_weight": 0.5,
      "final_weight": 0.5
    },
    "38268.538": {
      "votes": {},
      "initial_weight": 0.5,
      "final_weight": 0.5
    },
    "38268.111": {
      "votes": {},
      "initial_weight": 0.5,
      "final_weight": 0.5
    },
    "38268.170": {
      "votes": {},
      "initial_weight": 0.5,
      "final_weight": 0.5
    },
    "38268.410": {
      "votes": {},
      "initial_weight": 0.5,
      "final_weight": 0.5
    },
    "38268.491": {
      "votes": {},
      "initial_weight": 0.5,
      "final_weight": 0.5
    },
    "38268.415": {
      "votes": {},
      "initial_weight": 0.5,
      "final_weight": 0.5
    },
    "38268.412": {
      "votes": {},
      "initial_weight": 0.5,
      "final_weight": 0.5
    },
    "38268.489": {
      "votes": {},
      "initial_weight": 0.5,
      "final_weight": 0.5
    },
    "38268.315": {
      "votes": {},
      "initial_weight": 0.5,
      "final_weight": 0.5
    },
    "38268.39": {
      "votes": {},
      "initial_weight": 0.5,
      "final_weight": 0.5
    },
    "38268.194": {
      "votes": {},
      "initial_weight": 0.5,
      "final_weight": 0.6
    },
    "38268.396": {
      "votes": {},
      "initial_weight": 0.5,
      "final_weight": 0.6
    },
    "38268.406": {
      "votes": {},
      "initial_weight": 0.5,
      "final_weight": 0.5
    },
    "38268.408": {
      "votes": {},
      "initial_weight": 0.5,
      "final_weight": 0.5
    },
    "38268.67": {
      "votes": {},
      "initial_weight": 0.5,
      "final_weight": 0.5
    },
    "38268.190": {
      "votes": {},
      "initial_weight": 0.5,
      "final_weight": 0.5
    },
    "38268.463": {
      "votes": {},
      "initial_weight": 0.5,
      "final_weight": 0.5
    },
    "38268.276": {
      "votes": {},
      "initial_weight": 0.5,
      "final_weight": 0.6323529411764706
    },
    "38268.317": {
      "votes": {},
      "initial_weight": 0.5,
      "final_weight": 0.22795432651160547
    },
    "38268.465": {
      "votes": {},
      "initial_weight": 0.5,
      "final_weight": 0.5
    },
    "38268.596": {
      "votes": {},
      "initial_weight": 0.5,
      "final_weight": 0.1951219512195122
    },
    "38268.542": {
      "votes": {},
      "initial_weight": 0.5,
      "final_weight": 0.5
    },
    "38268.544": {
      "votes": {},
      "initial_weight": 0.5,
      "final_weight": 0.5
    },
    "38268.288": {
      "votes": {},
      "initial_weight": 0.5,
      "final_weight": 0.5
    },
    "38268.290": {
      "votes": {},
      "initial_weight": 0.5,
      "final_weight": 0.6
    },
    "38268.380": {
      "votes": {},
      "initial_weight": 0.5,
      "final_weight": 0.5
    },
    "38268.457": {
      "votes": {},
      "initial_weight": 0.5,
      "final_weight": 0.5
    },
    "38268.485": {
      "votes": {},
      "initial_weight": 0.5,
      "final_weight": 0.5
    },
    "38268.530": {
      "votes": {},
      "initial_weight": 0.5,
      "final_weight": 0.5
    },
    "38268.429": {
      "votes": {},
      "initial_weight": 0.5,
      "final_weight": 0.5
    },
    "38268.382": {
      "votes": {},
      "initial_weight": 0.5,
      "final_weight": 0.6
    },
    "38268.389": {
      "votes": {},
      "initial_weight": 0.5,
      "final_weight": 0.5
    },
    "38268.235": {
      "votes": {},
      "initial_weight": 0.5,
      "final_weight": 0.5004364810223685
    },
    "38268.392": {
      "votes": {},
      "initial_weight": 0.5,
      "final_weight": 0.5
    },
    "38268.504": {
      "votes": {},
      "initial_weight": 0.5,
      "final_weight": 0.5
    },
    "38268.510": {
      "votes": {},
      "initial_weight": 0.5,
      "final_weight": 0.4
    },
    "38268.196": {
      "votes": {
        "4": 1
      },
      "initial_weight": 1.0,
      "final_weight": 1.0
    },
    "38268.198": {
      "votes": {
        "1": 1
      },
      "initial_weight": 0.25,
      "final_weight": 0.25
    },
    "38268.188": {
      "votes": {
        "4": 1
      },
      "initial_weight": 1.0,
      "final_weight": 1.0
    },
    "38268.481": {
      "votes": {},
      "initial_weight": 0.5,
      "final_weight": 0.5
    },
    "38268.119": {
      "votes": {},
      "initial_weight": 0.5,
      "final_weight": 0.5
    },
    "38268.479": {
      "votes": {},
      "initial_weight": 0.5,
      "final_weight": 0.5
    },
    "38268.178": {
      "votes": {},
      "initial_weight": 0.5,
      "final_weight": 0.5
    },
    "38268.233": {
      "votes": {},
      "initial_weight": 0.5,
      "final_weight": 0.5
    },
    "38268.473": {
      "votes": {},
      "initial_weight": 0.5,
      "final_weight": 0.5
    },
    "38268.611": {
      "votes": {},
      "initial_weight": 0.5,
      "final_weight": 0.5
    },
    "38268.449": {
      "votes": {},
      "initial_weight": 0.5,
      "final_weight": 0.5
    },
    "38268.469": {
      "votes": {},
      "initial_weight": 0.5,
      "final_weight": 0.5
    },
    "38268.501": {
      "votes": {},
      "initial_weight": 0.5,
      "final_weight": 0.5
    },
    "38268.471": {
      "votes": {},
      "initial_weight": 0.5,
      "final_weight": 0.5
    },
    "38268.551": {
      "votes": {},
      "initial_weight": 0.5,
      "final_weight": 0.6
    },
    "38268.174": {
      "votes": {},
      "initial_weight": 0.5,
      "final_weight": 0.75
    },
    "38268.184": {
      "votes": {},
      "initial_weight": 0.5,
      "final_weight": 0.5
    },
    "38268.186": {
      "votes": {},
      "initial_weight": 0.5,
      "final_weight": 0.5
    },
    "38268.33": {
      "votes": {},
      "initial_weight": 0.5,
      "final_weight": 0.5
    },
    "38268.35": {
      "votes": {},
      "initial_weight": 0.5,
      "final_weight": 0.4
    },
    "38268.37": {
      "votes": {},
      "initial_weight": 0.5,
      "final_weight": 0.5
    },
    "38268.208": {
      "votes": {},
      "initial_weight": 0.5,
      "final_weight": 0.5
    },
    "38268.212": {
      "votes": {},
      "initial_weight": 0.5,
      "final_weight": 0.6
    },
    "38268.247": {
      "votes": {},
      "initial_weight": 0.5,
      "final_weight": 0.75
    },
    "38268.251": {
      "votes": {},
      "initial_weight": 0.5,
      "final_weight": 0.5
    },
    "38268.200": {
      "votes": {},
      "initial_weight": 0.5,
      "final_weight": 0.6644295302013423
    },
    "38268.343": {
      "votes": {},
      "initial_weight": 0.5,
      "final_weight": 0.30487804878048785
    },
    "38268.367": {
      "votes": {},
      "initial_weight": 0.5,
      "final_weight": 0.75
    },
    "38268.164": {
      "votes": {},
      "initial_weight": 0.5,
      "final_weight": 0.5
    },
    "38268.341": {
      "votes": {},
      "initial_weight": 0.5,
      "final_weight": 0.5
    },
    "38268.532": {
      "votes": {},
      "initial_weight": 0.5,
      "final_weight": 0.5
    },
    "38268.534": {
      "votes": {},
      "initial_weight": 0.5,
      "final_weight": 0.5
    },
    "38268.53": {
      "votes": {},
      "initial_weight": 0.5,
      "final_weight": 0.7737556561085973
    },
    "38268.204": {
      "votes": {
        "0": 1
      },
      "initial_weight": 0.0,
      "final_weight": 0.0
    },
    "38268.180": {
      "votes": {},
      "initial_weight": 0.5,
      "final_weight": 0.5
    },
    "38268.372": {
      "votes": {},
      "initial_weight": 0.5,
      "final_weight": 0.5
    },
    "38268.206": {
      "votes": {},
      "initial_weight": 0.5,
      "final_weight": 0.5
    },
    "38268.540": {
      "votes": {},
      "initial_weight": 0.5,
      "final_weight": 0.5
    },
    "38268.400": {
      "votes": {},
      "initial_weight": 0.5,
      "final_weight": 0.5
    },
    "38268.398": {
      "votes": {},
      "initial_weight": 0.5,
      "final_weight": 0.5
    },
    "38268.274": {
      "votes": {},
      "initial_weight": 0.5,
      "final_weight": 0.5
    },
    "38268.270": {
      "votes": {},
      "initial_weight": 0.5,
      "final_weight": 0.6
    },
    "38268.280": {
      "votes": {},
      "initial_weight": 0.5,
      "final_weight": 0.5
    },
    "38268.319": {
      "votes": {},
      "initial_weight": 0.5,
      "final_weight": 0.592438486821175
    },
    "38268.487": {
      "votes": {},
      "initial_weight": 0.5,
      "final_weight": 0.5
    },
    "38268.599": {
      "votes": {},
      "initial_weight": 0.5,
      "final_weight": 0.75
    },
    "38268.605": {
      "votes": {},
      "initial_weight": 0.5,
      "final_weight": 0.5
    },
    "38268.292": {
      "votes": {},
      "initial_weight": 0.5,
      "final_weight": 0.5
    },
    "38268.329": {
      "votes": {},
      "initial_weight": 0.5,
      "final_weight": 0.5
    },
    "38268.547": {
      "votes": {},
      "initial_weight": 0.5,
      "final_weight": 0.5
    },
    "38268.387": {
      "votes": {},
      "initial_weight": 0.5,
      "final_weight": 0.5
    },
    "38268.237": {
      "votes": {},
      "initial_weight": 0.5,
      "final_weight": 0.5704411642092976
    },
    "38268.333": {
      "votes": {},
      "initial_weight": 0.5,
      "final_weight": 0.6
    },
    "38268.506": {
      "votes": {},
      "initial_weight": 0.5,
      "final_weight": 0.5
    },
    "38268.508": {
      "votes": {},
      "initial_weight": 0.5,
      "final_weight": 0.5
    },
    "38268.512": {
      "votes": {},
      "initial_weight": 0.5,
      "final_weight": 0.5
    },
    "38268.553": {
      "votes": {},
      "initial_weight": 0.5,
      "final_weight": 0.5
    },
    "38268.257": {
      "votes": {},
      "initial_weight": 0.5,
      "final_weight": 0.5
    },
    "38268.259": {
      "votes": {},
      "initial_weight": 0.5,
      "final_weight": 0.5
    },
    "38268.216": {
      "votes": {},
      "initial_weight": 0.5,
      "final_weight": 0.5
    },
    "38268.210": {
      "votes": {},
      "initial_weight": 0.5,
      "final_weight": 0.5
    },
    "38268.249": {
      "votes": {},
      "initial_weight": 0.5,
      "final_weight": 0.5
    },
    "38268.453": {
      "votes": {},
      "initial_weight": 0.5,
      "final_weight": 0.5
    },
    "38268.202": {
      "votes": {},
      "initial_weight": 0.5,
      "final_weight": 0.5
    },
    "38268.355": {
      "votes": {},
      "initial_weight": 0.5,
      "final_weight": 0.4
    },
    "38268.361": {
      "votes": {},
      "initial_weight": 0.5,
      "final_weight": 0.6
    },
    "38268.345": {
      "votes": {},
      "initial_weight": 0.5,
      "final_weight": 0.6
    },
    "38268.347": {
      "votes": {},
      "initial_weight": 0.5,
      "final_weight": 0.6
    },
    "38268.351": {
      "votes": {},
      "initial_weight": 0.5,
      "final_weight": 0.4
    },
    "38268.365": {
      "votes": {},
      "initial_weight": 0.5,
      "final_weight": 0.5
    },
    "38268.370": {
      "votes": {},
      "initial_weight": 0.5,
      "final_weight": 0.5
    },
    "38268.522": {
      "votes": {},
      "initial_weight": 0.5,
      "final_weight": 0.5
    },
    "38268.61": {
      "votes": {},
      "initial_weight": 0.5,
      "final_weight": 0.6
    },
    "38268.225": {
      "votes": {},
      "initial_weight": 0.5,
      "final_weight": 0.5
    },
    "38268.520": {
      "votes": {},
      "initial_weight": 0.5,
      "final_weight": 0.5
    },
    "38268.272": {
      "votes": {},
      "initial_weight": 0.5,
      "final_weight": 0.5
    },
    "38268.321": {
      "votes": {},
      "initial_weight": 0.5,
      "final_weight": 0.5
    },
    "38268.323": {
      "votes": {},
      "initial_weight": 0.5,
      "final_weight": 0.75
    },
    "38268.327": {
      "votes": {},
      "initial_weight": 0.5,
      "final_weight": 0.7737556561085973
    },
    "38268.601": {
      "votes": {},
      "initial_weight": 0.5,
      "final_weight": 0.5
    },
    "38268.603": {
      "votes": {},
      "initial_weight": 0.5,
      "final_weight": 0.5
    },
    "38268.297": {
      "votes": {},
      "initial_weight": 0.5,
      "final_weight": 0.504950495049505
    },
    "38268.299": {
      "votes": {},
      "initial_weight": 0.5,
      "final_weight": 0.4
    },
    "38268.311": {
      "votes": {},
      "initial_weight": 0.5,
      "final_weight": 0.5
    },
    "38268.335": {
      "votes": {},
      "initial_weight": 0.5,
      "final_weight": 0.5
    },
    "38268.337": {
      "votes": {},
      "initial_weight": 0.5,
      "final_weight": 0.5
    },
    "38268.394": {
      "votes": {},
      "initial_weight": 0.5,
      "final_weight": 0.5
    },
    "38268.357": {
      "votes": {},
      "initial_weight": 0.5,
      "final_weight": 0.5
    },
    "38268.363": {
      "votes": {},
      "initial_weight": 0.5,
      "final_weight": 0.5
    },
    "38268.349": {
      "votes": {},
      "initial_weight": 0.5,
      "final_weight": 0.5
    },
    "38268.353": {
      "votes": {},
      "initial_weight": 0.5,
      "final_weight": 0.5
    },
    "38268.63": {
      "votes": {},
      "initial_weight": 0.5,
      "final_weight": 0.5
    },
    "38268.325": {
      "votes": {},
      "initial_weight": 0.5,
      "final_weight": 0.5
    },
    "38268.477": {
      "votes": {},
      "initial_weight": 0.5,
      "final_weight": 0.5
    },
    "38268.556": {
      "votes": {},
      "initial_weight": 0.5,
      "final_weight": 0.6
    },
    "38268.559": {
      "votes": {},
      "initial_weight": 0.5,
      "final_weight": 0.5
    },
    "38268.307": {
      "votes": {},
      "initial_weight": 0.5,
      "final_weight": 0.6
    },
    "38268.331": {
      "votes": {},
      "initial_weight": 0.5,
      "final_weight": 0.5
    },
    "38268.301": {
      "votes": {},
      "initial_weight": 0.5,
      "final_weight": 0.5
    },
    "38268.303": {
      "votes": {},
      "initial_weight": 0.5,
      "final_weight": 0.5
    },
    "38268.305": {
      "votes": {},
      "initial_weight": 0.5,
      "final_weight": 0.5
    },
    "38268.374": {
      "votes": {},
      "initial_weight": 0.5,
      "final_weight": 0.5
    },
    "38268.309": {
      "votes": {},
      "initial_weight": 0.5,
      "final_weight": 0.5
    },
    "38268.516": {
      "votes": {},
      "initial_weight": 0.5,
      "final_weight": 0.5
    },
    "38268.518": {
      "votes": {},
      "initial_weight": 0.5,
      "final_weight": 0.5
    }
  },
  "edges": {
    "38268.3": {
      "successor_id": "38268.0",
      "relation": 0.0
    },
    "38268.7": {
      "successor_id": "38268.3",
      "relation": 1.0
    },
    "38268.13": {
      "successor_id": "38268.3",
      "relation": 1.0
    },
    "38268.25": {
      "successor_id": "38268.3",
      "relation": -1.0
    },
    "38268.84": {
      "successor_id": "38268.3",
      "relation": 1.0
    },
    "38268.219": {
      "successor_id": "38268.3",
      "relation": -1.0
    },
    "38268.89": {
      "successor_id": "38268.7",
      "relation": -1.0
    },
    "38268.5": {
      "successor_id": "38268.7",
      "relation": 1.0
    },
    "38268.23": {
      "successor_id": "38268.7",
      "relation": 1.0
    },
    "38268.575": {
      "successor_id": "38268.7",
      "relation": -1.0
    },
    "38268.151": {
      "successor_id": "38268.7",
      "relation": -1.0
    },
    "38268.95": {
      "successor_id": "38268.13",
      "relation": -1.0
    },
    "38268.87": {
      "successor_id": "38268.13",
      "relation": -1.0
    },
    "38268.417": {
      "successor_id": "38268.13",
      "relation": 1.0
    },
    "38268.421": {
      "successor_id": "38268.13",
      "relation": 1.0
    },
    "38268.461": {
      "successor_id": "38268.13",
      "relation": 1.0
    },
    "38268.105": {
      "successor_id": "38268.25",
      "relation": -1.0
    },
    "38268.261": {
      "successor_id": "38268.25",
      "relation": 1.0
    },
    "38268.563": {
      "successor_id": "38268.25",
      "relation": 1.0
    },
    "38268.78": {
      "successor_id": "38268.84",
      "relation": 1.0
    },
    "38268.239": {
      "successor_id": "38268.84",
      "relation": 1.0
    },
    "38268.431": {
      "successor_id": "38268.84",
      "relation": 1.0
    },
    "38268.433": {
      "successor_id": "38268.84",
      "relation": -1.0
    },
    "38268.137": {
      "successor_id": "38268.219",
      "relation": 1.0
    },
    "38268.153": {
      "successor_id": "38268.219",
      "relation": 1.0
    },
    "38268.27": {
      "successor_id": "38268.219",
      "relation": 1.0
    },
    "38268.227": {
      "successor_id": "38268.219",
      "relation": -1.0
    },
    "38268.573": {
      "successor_id": "38268.219",
      "relation": -1.0
    },
    "38268.93": {
      "successor_id": "38268.89",
      "relation": 1.0
    },
    "38268.115": {
      "successor_id": "38268.89",
      "relation": -1.0
    },
    "38268.141": {
      "successor_id": "38268.89",
      "relation": 1.0
    },
    "38268.313": {
      "successor_id": "38268.282",
      "relation": -1.0
    },
    "38268.41": {
      "successor_id": "38268.5",
      "relation": 1.0
    },
    "38268.19": {
      "successor_id": "38268.5",
      "relation": -1.0
    },
    "38268.402": {
      "successor_id": "38268.5",
      "relation": 1.0
    },
    "38268.584": {
      "successor_id": "38268.5",
      "relation": -1.0
    },
    "38268.65": {
      "successor_id": "38268.23",
      "relation": 1.0
    },
    "38268.75": {
      "successor_id": "38268.23",
      "relation": 1.0
    },
    "38268.282": {
      "successor_id": "38268.23",
      "relation": -1.0
    },
    "38268.588": {
      "successor_id": "38268.23",
      "relation": -1.0
    },
    "38268.594": {
      "successor_id": "38268.575",
      "relation": -1.0
    },
    "38268.139": {
      "successor_id": "38268.151",
      "relation": -1.0
    },
    "38268.182": {
      "successor_id": "38268.433",
      "relation": 1.0
    },
    "38268.295": {
      "successor_id": "38268.151",
      "relation": -1.0
    },
    "38268.339": {
      "successor_id": "38268.151",
      "relation": -1.0
    },
    "38268.378": {
      "successor_id": "38268.151",
      "relation": 1.0
    },
    "38268.384": {
      "successor_id": "38268.151",
      "relation": 1.0
    },
    "38268.97": {
      "successor_id": "38268.95",
      "relation": 1.0
    },
    "38268.99": {
      "successor_id": "38268.95",
      "relation": -1.0
    },
    "38268.101": {
      "successor_id": "38268.95",
      "relation": 1.0
    },
    "38268.117": {
      "successor_id": "38268.87",
      "relation": -1.0
    },
    "38268.176": {
      "successor_id": "38268.87",
      "relation": -1.0
    },
    "38268.231": {
      "successor_id": "38268.87",
      "relation": 1.0
    },
    "38268.376": {
      "successor_id": "38268.87",
      "relation": 1.0
    },
    "38268.419": {
      "successor_id": "38268.417",
      "relation": 1.0
    },
    "38268.467": {
      "successor_id": "38268.417",
      "relation": -1.0
    },
    "38268.499": {
      "successor_id": "38268.417",
      "relation": 1.0
    },
    "38268.423": {
      "successor_id": "38268.421",
      "relation": 1.0
    },
    "38268.425": {
      "successor_id": "38268.421",
      "relation": 1.0
    },
    "38268.427": {
      "successor_id": "38268.421",
      "relation": 1.0
    },
    "38268.447": {
      "successor_id": "38268.421",
      "relation": -1.0
    },
    "38268.549": {
      "successor_id": "38268.461",
      "relation": -1.0
    },
    "38268.123": {
      "successor_id": "38268.105",
      "relation": 1.0
    },
    "38268.286": {
      "successor_id": "38268.105",
      "relation": -1.0
    },
    "38268.82": {
      "successor_id": "38268.261",
      "relation": 1.0
    },
    "38268.125": {
      "successor_id": "38268.261",
      "relation": 1.0
    },
    "38268.31": {
      "successor_id": "38268.261",
      "relation": 1.0
    },
    "38268.266": {
      "successor_id": "38268.261",
      "relation": -1.0
    },
    "38268.172": {
      "successor_id": "38268.538",
      "relation": -1.0
    },
    "38268.528": {
      "successor_id": "38268.563",
      "relation": -1.0
    },
    "38268.526": {
      "successor_id": "38268.563",
      "relation": 1.0
    },
    "38268.561": {
      "successor_id": "38268.563",
      "relation": 1.0
    },
    "38268.451": {
      "successor_id": "38268.78",
      "relation": -1.0
    },
    "38268.494": {
      "successor_id": "38268.78",
      "relation": 1.0
    },
    "38268.496": {
      "successor_id": "38268.78",
      "relation": 1.0
    },
    "38268.241": {
      "successor_id": "38268.239",
      "relation": 1.0
    },
    "38268.243": {
      "successor_id": "38268.239",
      "relation": 1.0
    },
    "38268.245": {
      "successor_id": "38268.239",
      "relation": -1.0
    },
    "38268.455": {
      "successor_id": "38268.431",
      "relation": -1.0
    },
    "38268.168": {
      "successor_id": "38268.166",
      "relation": 1.0
    },
    "38268.435": {
      "successor_id": "38268.433",
      "relation": 1.0
    },
    "38268.437": {
      "successor_id": "38268.433",
      "relation": -1.0
    },
    "38268.157": {
      "successor_id": "38268.153",
      "relation": 1.0
    },
    "38268.162": {
      "successor_id": "38268.153",
      "relation": -1.0
    },
    "38268.359": {
      "successor_id": "38268.153",
      "relation": -1.0
    },
    "38268.43": {
      "successor_id": "38268.27",
      "relation": -1.0
    },
    "38268.51": {
      "successor_id": "38268.27",
      "relation": 1.0
    },
    "38268.45": {
      "successor_id": "38268.27",
      "relation": -1.0
    },
    "38268.127": {
      "successor_id": "38268.27",
      "relation": 1.0
    },
    "38268.166": {
      "successor_id": "38268.27",
      "relation": -1.0
    },
    "38268.229": {
      "successor_id": "38268.227",
      "relation": 1.0
    },
    "38268.538": {
      "successor_id": "38268.227",
      "relation": -1.0
    },
    "38268.111": {
      "successor_id": "38268.93",
      "relation": -1.0
    },
    "38268.170": {
      "successor_id": "38268.115",
      "relation": 1.0
    },
    "38268.410": {
      "successor_id": "38268.115",
      "relation": 1.0
    },
    "38268.491": {
      "successor_id": "38268.115",
      "relation": -1.0
    },
    "38268.415": {
      "successor_id": "38268.115",
      "relation": 1.0
    },
    "38268.412": {
      "successor_id": "38268.141",
      "relation": -1.0
    },
    "38268.489": {
      "successor_id": "38268.141",
      "relation": 1.0
    },
    "38268.315": {
      "successor_id": "38268.313",
      "relation": 1.0
    },
    "38268.39": {
      "successor_id": "38268.19",
      "relation": 1.0
    },
    "38268.194": {
      "successor_id": "38268.19",
      "relation": 1.0
    },
    "38268.396": {
      "successor_id": "38268.19",
      "relation": -1.0
    },
    "38268.406": {
      "successor_id": "38268.402",
      "relation": 1.0
    },
    "38268.408": {
      "successor_id": "38268.402",
      "relation": -1.0
    },
    "38268.67": {
      "successor_id": "38268.65",
      "relation": -1.0
    },
    "38268.190": {
      "successor_id": "38268.65",
      "relation": -1.0
    },
    "38268.463": {
      "successor_id": "38268.65",
      "relation": 1.0
    },
    "38268.276": {
      "successor_id": "38268.75",
      "relation": -1.0
    },
    "38268.317": {
      "successor_id": "38268.282",
      "relation": 1.0
    },
    "38268.465": {
      "successor_id": "38268.282",
      "relation": -1.0
    },
    "38268.596": {
      "successor_id": "38268.594",
      "relation": 1.0
    },
    "38268.542": {
      "successor_id": "38268.139",
      "relation": 1.0
    },
    "38268.544": {
      "successor_id": "38268.139",
      "relation": 1.0
    },
    "38268.288": {
      "successor_id": "38268.182",
      "relation": -1.0
    },
    "38268.290": {
      "successor_id": "38268.182",
      "relation": 1.0
    },
    "38268.380": {
      "successor_id": "38268.182",
      "relation": 1.0
    },
    "38268.457": {
      "successor_id": "38268.182",
      "relation": -1.0
    },
    "38268.485": {
      "successor_id": "38268.182",
      "relation": -1.0
    },
    "38268.530": {
      "successor_id": "38268.295",
      "relation": -1.0
    },
    "38268.429": {
      "successor_id": "38268.339",
      "relation": 1.0
    },
    "38268.382": {
      "successor_id": "38268.378",
      "relation": -1.0
    },
    "38268.389": {
      "successor_id": "38268.378",
      "relation": 1.0
    },
    "38268.235": {
      "successor_id": "38268.384",
      "relation": -1.0
    },
    "38268.392": {
      "successor_id": "38268.384",
      "relation": 1.0
    },
    "38268.504": {
      "successor_id": "38268.97",
      "relation": 1.0
    },
    "38268.510": {
      "successor_id": "38268.97",
      "relation": 1.0
    },
    "38268.196": {
      "successor_id": "38268.99",
      "relation": -1.0
    },
    "38268.198": {
      "successor_id": "38268.99",
      "relation": 1.0
    },
    "38268.188": {
      "successor_id": "38268.101",
      "relation": -1.0
    },
    "38268.481": {
      "successor_id": "38268.101",
      "relation": 1.0
    },
    "38268.119": {
      "successor_id": "38268.117",
      "relation": 1.0
    },
    "38268.479": {
      "successor_id": "38268.117",
      "relation": -1.0
    },
    "38268.178": {
      "successor_id": "38268.176",
      "relation": 1.0
    },
    "38268.233": {
      "successor_id": "38268.231",
      "relation": -1.0
    },
    "38268.473": {
      "successor_id": "38268.376",
      "relation": -1.0
    },
    "38268.611": {
      "successor_id": "38268.376",
      "relation": 1.0
    },
    "38268.449": {
      "successor_id": "38268.419",
      "relation": 1.0
    },
    "38268.469": {
      "successor_id": "38268.467",
      "relation": -1.0
    },
    "38268.501": {
      "successor_id": "38268.499",
      "relation": 1.0
    },
    "38268.471": {
      "successor_id": "38268.447",
      "relation": -1.0
    },
    "38268.551": {
      "successor_id": "38268.549",
      "relation": -1.0
    },
    "38268.174": {
      "successor_id": "38268.82",
      "relation": -1.0
    },
    "38268.184": {
      "successor_id": "38268.125",
      "relation": -1.0
    },
    "38268.186": {
      "successor_id": "38268.125",
      "relation": -1.0
    },
    "38268.33": {
      "successor_id": "38268.31",
      "relation": 1.0
    },
    "38268.35": {
      "successor_id": "38268.31",
      "relation": 1.0
    },
    "38268.37": {
      "successor_id": "38268.31",
      "relation": -1.0
    },
    "38268.208": {
      "successor_id": "38268.31",
      "relation": -1.0
    },
    "38268.212": {
      "successor_id": "38268.31",
      "relation": -1.0
    },
    "38268.247": {
      "successor_id": "38268.245",
      "relation": -1.0
    },
    "38268.251": {
      "successor_id": "38268.245",
      "relation": 1.0
    },
    "38268.200": {
      "successor_id": "38268.157",
      "relation": -1.0
    },
    "38268.343": {
      "successor_id": "38268.157",
      "relation": 1.0
    },
    "38268.367": {
      "successor_id": "38268.157",
      "relation": -1.0
    },
    "38268.164": {
      "successor_id": "38268.162",
      "relation": 1.0
    },
    "38268.341": {
      "successor_id": "38268.162",
      "relation": 1.0
    },
    "38268.532": {
      "successor_id": "38268.43",
      "relation": 1.0
    },
    "38268.534": {
      "successor_id": "38268.43",
      "relation": -1.0
    },
    "38268.53": {
      "successor_id": "38268.51",
      "relation": -1.0
    },
    "38268.204": {
      "successor_id": "38268.51",
      "relation": -1.0
    },
    "38268.180": {
      "successor_id": "38268.127",
      "relation": -1.0
    },
    "38268.372": {
      "successor_id": "38268.127",
      "relation": -1.0
    },
    "38268.206": {
      "successor_id": "38268.166",
      "relation": 1.0
    },
    "38268.540": {
      "successor_id": "38268.538",
      "relation": 1.0
    },
    "38268.400": {
      "successor_id": "38268.194",
      "relation": 1.0
    },
    "38268.398": {
      "successor_id": "38268.396",
      "relation": 1.0
    },
    "38268.274": {
      "successor_id": "38268.276",
      "relation": 1.0
    },
    "38268.270": {
      "successor_id": "38268.276",
      "relation": 1.0
    },
    "38268.280": {
      "successor_id": "38268.276",
      "relation": -1.0
    },
    "38268.319": {
      "successor_id": "38268.317",
      "relation": -1.0
    },
    "38268.487": {
      "successor_id": "38268.317",
      "relation": -1.0
    },
    "38268.599": {
      "successor_id": "38268.596",
      "relation": -1.0
    },
    "38268.605": {
      "successor_id": "38268.596",
      "relation": -1.0
    },
    "38268.292": {
      "successor_id": "38268.290",
      "relation": 1.0
    },
    "38268.329": {
      "successor_id": "38268.290",
      "relation": 1.0
    },
    "38268.547": {
      "successor_id": "38268.290",
      "relation": -1.0
    },
    "38268.387": {
      "successor_id": "38268.382",
      "relation": 1.0
    },
    "38268.237": {
      "successor_id": "38268.235",
      "relation": -1.0
    },
    "38268.333": {
      "successor_id": "38268.235",
      "relation": 1.0
    },
    "38268.506": {
      "successor_id": "38268.504",
      "relation": -1.0
    },
    "38268.508": {
      "successor_id": "38268.504",
      "relation": 1.0
    },
    "38268.512": {
      "successor_id": "38268.510",
      "relation": -1.0
    },
    "38268.553": {
      "successor_id": "38268.551",
      "relation": 1.0
    },
    "38268.257": {
      "successor_id": "38268.174",
      "relation": 1.0
    },
    "38268.259": {
      "successor_id": "38268.174",
      "relation": 1.0
    },
    "38268.216": {
      "successor_id": "38268.35",
      "relation": -1.0
    },
    "38268.210": {
      "successor_id": "38268.212",
      "relation": 1.0
    },
    "38268.249": {
      "successor_id": "38268.247",
      "relation": 1.0
    },
    "38268.453": {
      "successor_id": "38268.247",
      "relation": 1.0
    },
    "38268.202": {
      "successor_id": "38268.200",
      "relation": 1.0
    },
    "38268.355": {
      "successor_id": "38268.200",
      "relation": -1.0
    },
    "38268.361": {
      "successor_id": "38268.200",
      "relation": 1.0
    },
    "38268.345": {
      "successor_id": "38268.343",
      "relation": -1.0
    },
    "38268.347": {
      "successor_id": "38268.343",
      "relation": -1.0
    },
    "38268.351": {
      "successor_id": "38268.343",
      "relation": 1.0
    },
    "38268.365": {
      "successor_id": "38268.367",
      "relation": 1.0
    },
    "38268.370": {
      "successor_id": "38268.367",
      "relation": 1.0
    },
    "38268.522": {
      "successor_id": "38268.347",
      "relation": 1.0
    },
    "38268.61": {
      "successor_id": "38268.53",
      "relation": 1.0
    },
    "38268.225": {
      "successor_id": "38268.53",
      "relation": 1.0
    },
    "38268.520": {
      "successor_id": "38268.204",
      "relation": -1.0
    },
    "38268.272": {
      "successor_id": "38268.270",
      "relation": 1.0
    },
    "38268.321": {
      "successor_id": "38268.319",
      "relation": 1.0
    },
    "38268.323": {
      "successor_id": "38268.319",
      "relation": 1.0
    },
    "38268.327": {
      "successor_id": "38268.319",
      "relation": -1.0
    },
    "38268.601": {
      "successor_id": "38268.599",
      "relation": 1.0
    },
    "38268.603": {
      "successor_id": "38268.599",
      "relation": 1.0
    },
    "38268.297": {
      "successor_id": "38268.237",
      "relation": 1.0
    },
    "38268.299": {
      "successor_id": "38268.237",
      "relation": 1.0
    },
    "38268.311": {
      "successor_id": "38268.237",
      "relation": -1.0
    },
    "38268.335": {
      "successor_id": "38268.333",
      "relation": 1.0
    },
    "38268.337": {
      "successor_id": "38268.333",
      "relation": 1.0
    },
    "38268.394": {
      "successor_id": "38268.333",
      "relation": -1.0
    },
    "38268.357": {
      "successor_id": "38268.355",
      "relation": -1.0
    },
    "38268.363": {
      "successor_id": "38268.361",
      "relation": 1.0
    },
    "38268.349": {
      "successor_id": "38268.345",
      "relation": 1.0
    },
    "38268.353": {
      "successor_id": "38268.351",
      "relation": -1.0
    },
    "38268.63": {
      "successor_id": "38268.61",
      "relation": 1.0
    },
    "38268.325": {
      "successor_id": "38268.323",
      "relation": 1.0
    },
    "38268.477": {
      "successor_id": "38268.323",
      "relation": 1.0
    },
    "38268.556": {
      "successor_id": "38268.327",
      "relation": 1.0
    },
    "38268.559": {
      "successor_id": "38268.327",
      "relation": 1.0
    },
    "38268.307": {
      "successor_id": "38268.297",
      "relation": 1.0
    },
    "38268.331": {
      "successor_id": "38268.297",
      "relation": -1.0
    },
    "38268.301": {
      "successor_id": "38268.299",
      "relation": -1.0
    },
    "38268.303": {
      "successor_id": "38268.299",
      "relation": -1.0
    },
    "38268.305": {
      "successor_id": "38268.299",
      "relation": 1.0
    },
    "38268.374": {
      "successor_id": "38268.556",
      "relation": 1.0
    },
    "38268.309": {
      "successor_id": "38268.307",
      "relation": -1.0
    },
    "38268.516": {
      "successor_id": "38268.307",
      "relation": 1.0
    },
    "38268.518": {
      "successor_id": "38268.307",
      "relation": 1.0
    }
  }
}