{
  "nodes": {
    "43251.52": {
      "votes": {
        "4": 2
      },
      "initial_weight": 1.0,
      "final_weight": 1.0
    },
    "43251.133": {
      "votes": {
        "2": 1
      },
      "initial_weight": 0.5,
      "final_weight": 0.5
    },
    "43251.129": {
      "votes": {},
      "initial_weight": 0.5,
      "final_weight": 0.5
    },
    "43251.50": {
      "votes": {},
      "initial_weight": 0.5,
      "final_weight": 0.5
    },
    "43251.3": {
      "votes": {
        "0": 2,
        "1": 1
      },
      "initial_weight": 0.08333333333333333,
      "final_weight": 0.011364387380021601
    },
    "43251.29": {
      "votes": {
        "4": 1
      },
      "initial_weight": 1.0,
      "final_weight": 1.0
    },
    "43251.7": {
      "votes": {
        "1": 1
      },
      "initial_weight": 0.25,
      "final_weight": 0.11362016856279333
    },
    "43251.23": {
      "votes": {
        "1": 1
      },
      "initial_weight": 0.25,
      "final_weight": 0.18382352941176472
    },
    "43251.64": {
      "votes": {
        "2": 1
      },
      "initial_weight": 0.5,
      "final_weight": 0.5
    },
    "43251.66": {
      "votes": {
        "1": 1
      },
      "initial_weight": 0.25,
      "final_weight": 0.25
    },
    "43251.123": {
      "votes": {
        "1": 1
      },
      "initial_weight": 0.25,
      "final_weight": 0.25
    },
    "43251.125": {
      "votes": {
        "2": 1
      },
      "initial_weight": 0.5,
      "final_weight": 0.5
    },
    "43251.70": {
      "votes": {
        "2": 1
      },
      "initial_weight": 0.5,
      "final_weight": 0.6
    },
    "43251.135": {
      "votes": {
        "3": 1
      },
      "initial_weight": 0.75,
      "final_weight": 0.75
    },
    "43251.94": {
      "votes": {},
      "initial_weight": 0.5,
      "final_weight": 0.5
    },
    "43251.72": {
      "votes": {},
      "initial_weight": 0.5,
      "final_weight": 0.5
    },
    "43251.21": {
      "votes": {
        "3": 1
      },
      "initial_weight": 0.75,
      "final_weight": 0.8
    },
    "43251.31": {
      "votes": {
        "4": 1
      },
      "initial_weight": 1.0,
      "final_weight": 1.0
    },
    "43251.60": {
      "votes": {
        "4": 1
      },
      "initial_weight": 1.0,
      "final_weight": 1.0
    },
    "43251.137": {
      "votes": {
        "4": 1
      },
      "initial_weight": 1.0,
      "final_weight": 1.0
    },
    "43251.107": {
      "votes": {},
      "initial_weight": 0.5,
      "final_weight": 0.4
    },
    "43251.80": {
      "votes": {
        "4": 1
      },
      "initial_weight": 1.0,
      "final_weight": 1.0
    },
    "43251.131": {
      "votes": {},
      "initial_weight": 0.5,
      "final_weight": 0.5
    },
    "43251.82": {
      "votes": {
        "4": 1
      },
      "initial_weight": 1.0,
      "final_weight": 1.0
    },
    "43251.76": {
      "votes": {},
      "initial_weight": 0.5,
      "final_weight": 0.5
    },
    "43251.58": {
      "votes": {
        "4": 1
      },
      "initial_weight": 1.0,
      "final_weight": 1.0
    },
    "43251.15": {
      "votes": {
        "2": 1
      },
      "initial_weight": 0.5,
      "final_weight": 0.32
    },
    "43251.46": {
      "votes": {},
      "initial_weight": 0.5,
      "final_weight": 0.5
    },
    "43251.141": {
      "votes": {
        "3": 1
      },
      "initial_weight": 0.75,
      "final_weight": 0.75
    },
    "43251.37": {
      "votes": {
        "3": 1
      },
      "initial_weight": 0.75,
      "final_weight": 0.75
    },
    "43251.90": {
      "votes": {},
      "initial_weight": 0.5,
      "final_weight": 0.5
    },
    "43251.84": {
      "votes": {},
      "initial_weight": 0.5,
      "final_weight": 0.5
    },
    "43251.19": {
      "votes": {
        "4": 1
      },
      "initial_weight": 1.0,
      "final_weight": 1.0
    },
    "43251.54": {
      "votes": {
        "3": 1
      },
      "initial_weight": 0.75,
      "final_weight": 0.75
    },
    "43251.11": {
      "votes": {
        "1": 1
      },
      "initial_weight": 0.25,
      "final_weight": 0.20945040214477212
    },
    "43251.5": {
      "votes": {
        "1": 1
      },
      "initial_weight": 0.25,
      "final_weight": 0.18806352375484253
    },
    "43251.68": {
      "votes": {},
      "initial_weight": 0.5,
      "final_weight": 0.5
    },
    "43251.121": {
      "votes": {
        "3": 1
      },
      "initial_weight": 0.75,
      "final_weight": 0.75
    },
    "43251.114": {
      "votes": {},
      "initial_weight": 0.5,
      "final_weight": 0.5
    },
    "43251.48": {
      "votes": {
        "3": 1,
        "4": 1
      },
      "initial_weight": 0.875,
      "final_weight": 0.9237804878048781
    },
    "43251.116": {
      "votes": {},
      "initial_weight": 0.5,
      "final_weight": 0.5
    },
    "43251.74": {
      "votes": {},
      "initial_weight": 0.5,
      "final_weight": 0.5
    },
    "43251.27": {
      "votes": {
        "1": 1,
        "0": 1
      },
      "initial_weight": 0.125,
      "final_weight": 0.1
    },
    "43251.112": {
      "votes": {},
      "initial_weight": 0.5,
      "final_weight": 0.5
    },
    "43251.56": {
      "votes": {
        "4": 1
      },
      "initial_weight": 1.0,
      "final_weight": 1.0
    },
    "43251.33": {
      "votes": {
        "2": 1
      },
      "initial_weight": 0.5,
      "final_weight": 0.6
    },
    "43251.39": {
      "votes": {
        "4": 2
      },
      "initial_weight": 1.0,
      "final_weight": 1.0
    },
    "43251.35": {
      "votes": {},
      "initial_weight": 0.5,
      "final_weight": 0.5
    },
    "43251.119": {
      "votes": {
        "3": 1
      },
      "initial_weight": 0.75,
      "final_weight": 0.75
    },
    "43251.62": {
      "votes": {},
      "initial_weight": 0.5,
      "final_weight": 0.5
    },
    "43251.13": {
      "votes": {},
      "initial_weight": 0.5,
      "final_weight": 0.5
    },
    "43251.86": {
      "votes": {},
      "initial_weight": 0.5,
      "final_weight": 0.6
    },
    "43251.41": {
      "votes": {
        "1": 1,
        "0": 1
      },
      "initial_weight": 0.125,
      "final_weight": 0.11920177246970576
    },
    "43251.96": {
      "votes": {},
      "initial_weight": 0.5,
      "final_weight": 0.5
    },
    "43251.17": {
      "votes": {
        "3": 1
      },
      "initial_weight": 0.75,
      "final_weight": 0.84
    },
    "43251.88": {
      "votes": {
        "4": 1
      },
      "initial_weight": 1.0,
      "final_weight": 1.0
    },
    "43251.109": {
      "votes": {},
      "initial_weight": 0.5,
      "final_weight": 0.5
    },
    "43251.25": {
      "votes": {},
      "initial_weight": 0.5,
      "final_weight": 0.47058823529411764
    },
    "43251.127": {
      "votes": {},
      "initial_weight": 0.5,
      "final_weight": 0.5
    },
    "43251.78": {
      "votes": {
        "4": 1
      },
      "initial_weight": 1.0,
      "final_weight": 1.0
    },
    "43251.92": {
      "votes": {
        "3": 1,
        "4": 1
      },
      "initial_weight": 0.875,
      "final_weight": 0.9375
    },
    "43251.9": {
      "votes": {
        "1": 1
      },
      "initial_weight": 0.25,
      "final_weight": 0.25
    }
  },
  "edges": {
    "43251.5": {
      "successor_id": "43251.3",
      "relation": 1.0
    },
    "43251.27": {
      "successor_id": "43251.3",
      "relation": 1.0
    },
    "43251.39": {
      "successor_id": "43251.3",
      "relation": -1.0
    },
    "43251.41": {
      "successor_id": "43251.3",
      "relation": 1.0
    },
    "43251.48": {
      "successor_id": "43251.3",
      "relation": -1.0
    },
    "43251.52": {
      "successor_id": "43251.3",
      "relation": -1.0
    },
    "43251.66": {
      "successor_id": "43251.5",
      "relation": 1.0
    },
    "43251.92": {
      "successor_id": "43251.5",
      "relation": -1.0
    },
    "43251.7": {
      "successor_id": "43251.5",
      "relation": 1.0
    },
    "43251.56": {
      "successor_id": "43251.27",
      "relation": -1.0
    },
    "43251.64": {
      "successor_id": "43251.27",
      "relation": 1.0
    },
    "43251.121": {
      "successor_id": "43251.39",
      "relation": 1.0
    },
    "43251.123": {
      "successor_id": "43251.39",
      "relation": -1.0
    },
    "43251.137": {
      "successor_id": "43251.39",
      "relation": 1.0
    },
    "43251.11": {
      "successor_id": "43251.41",
      "relation": 1.0
    },
    "43251.54": {
      "successor_id": "43251.41",
      "relation": -1.0
    },
    "43251.15": {
      "successor_id": "43251.41",
      "relation": 1.0
    },
    "43251.50": {
      "successor_id": "43251.48",
      "relation": 1.0
    },
    "43251.21": {
      "successor_id": "43251.48",
      "relation": 1.0
    },
    "43251.112": {
      "successor_id": "43251.48",
      "relation": -1.0
    },
    "43251.70": {
      "successor_id": "43251.52",
      "relation": -1.0
    },
    "43251.29": {
      "successor_id": "43251.52",
      "relation": 1.0
    },
    "43251.68": {
      "successor_id": "43251.66",
      "relation": 1.0
    },
    "43251.76": {
      "successor_id": "43251.66",
      "relation": 1.0
    },
    "43251.78": {
      "successor_id": "43251.66",
      "relation": -1.0
    },
    "43251.94": {
      "successor_id": "43251.92",
      "relation": 1.0
    },
    "43251.96": {
      "successor_id": "43251.92",
      "relation": 1.0
    },
    "43251.60": {
      "successor_id": "43251.7",
      "relation": -1.0
    },
    "43251.23": {
      "successor_id": "43251.7",
      "relation": 1.0
    },
    "43251.25": {
      "successor_id": "43251.7",
      "relation": 1.0
    },
    "43251.141": {
      "successor_id": "43251.7",
      "relation": -1.0
    },
    "43251.17": {
      "successor_id": "43251.11",
      "relation": -1.0
    },
    "43251.107": {
      "successor_id": "43251.11",
      "relation": 1.0
    },
    "43251.9": {
      "successor_id": "43251.15",
      "relation": 1.0
    },
    "43251.58": {
      "successor_id": "43251.15",
      "relation": -1.0
    },
    "43251.19": {
      "successor_id": "43251.21",
      "relation": 1.0
    },
    "43251.125": {
      "successor_id": "43251.21",
      "relation": -1.0
    },
    "43251.114": {
      "successor_id": "43251.112",
      "relation": 1.0
    },
    "43251.116": {
      "successor_id": "43251.112",
      "relation": -1.0
    },
    "43251.72": {
      "successor_id": "43251.70",
      "relation": 1.0
    },
    "43251.46": {
      "successor_id": "43251.29",
      "relation": 1.0
    },
    "43251.62": {
      "successor_id": "43251.29",
      "relation": 1.0
    },
    "43251.82": {
      "successor_id": "43251.29",
      "relation": 1.0
    },
    "43251.31": {
      "successor_id": "43251.29",
      "relation": 1.0
    },
    "43251.133": {
      "successor_id": "43251.29",
      "relation": -1.0
    },
    "43251.80": {
      "successor_id": "43251.78",
      "relation": 1.0
    },
    "43251.119": {
      "successor_id": "43251.60",
      "relation": 1.0
    },
    "43251.33": {
      "successor_id": "43251.23",
      "relation": -1.0
    },
    "43251.37": {
      "successor_id": "43251.25",
      "relation": -1.0
    },
    "43251.13": {
      "successor_id": "43251.25",
      "relation": 1.0
    },
    "43251.135": {
      "successor_id": "43251.17",
      "relation": 1.0
    },
    "43251.109": {
      "successor_id": "43251.107",
      "relation": -1.0
    },
    "43251.86": {
      "successor_id": "43251.82",
      "relation": 1.0
    },
    "43251.90": {
      "successor_id": "43251.82",
      "relation": 1.0
    },
    "43251.74": {
      "successor_id": "43251.31",
      "relation": 1.0
    },
    "43251.88": {
      "successor_id": "43251.31",
      "relation": 1.0
    },
    "43251.35": {
      "successor_id": "43251.33",
      "relation": 1.0
    },
    "43251.84": {
      "successor_id": "43251.86",
      "relation": 1.0
    },
    "43251.127": {
      "successor_id": "43251.88",
      "relation": 1.0
    },
    "43251.129": {
      "successor_id": "43251.88",
      "relation": 1.0
    },
    "43251.131": {
      "successor_id": "43251.88",
      "relation": 1.0
    }
  }
}